spotify_token.py
spotify_token-1.0.0.dist-info/LICENSE
spotify_token-1.0.0.dist-info/METADATA
spotify_token-1.0.0.dist-info/WHEEL
spotify_token-1.0.0.dist-info/top_level.txt
spotify_token-1.0.0.dist-info/RECORD
