Metadata-Version: 1.1
Name: spotify-token
Version: 1.0.0
Summary: Python wrapper for Spotify Webplayer access token
Home-page: https://github.com/enriquegh/spotify-webplayer-token
Author: Enrique Gonzalez
Author-email: egonzalezh94@gmail.com
License: MIT
Keywords: wrapper,spotify
Platform: UNKNOWN
Classifier: Programming Language :: Python :: 3
Classifier: Intended Audience :: Developers
Classifier: License :: OSI Approved :: MIT License
Classifier: Topic :: Software Development :: Libraries
Classifier: Topic :: Utilities
